didjvu/__init__.py
didjvu/__main__.py
didjvu/cli.py
didjvu/didjvu.py
didjvu/djvu_support.py
didjvu/filetype.py
didjvu/fs.py
didjvu/gamera_support.py
didjvu/ipc.py
didjvu/templates.py
didjvu/temporary.py
didjvu/timestamp.py
didjvu/utils.py
didjvu/version.py
didjvu/xmp/__init__.py
didjvu/xmp/gexiv2_backend.py
didjvu/xmp/libxmp_backend.py
didjvu/xmp/namespaces.py
didjvu/xmp/pyexiv2_backend.py
didjvu-0.11.0.dist-info/licenses/COPYING
didjvu-0.11.0.dist-info/METADATA
didjvu-0.11.0.dist-info/WHEEL
didjvu-0.11.0.dist-info/entry_points.txt
didjvu-0.11.0.dist-info/top_level.txt
didjvu-0.11.0.dist-info/RECORD
