Metadata-Version: 2.4
Name: didjvu
Version: 0.11.0
Summary: DjVu encoder with foreground/background separation (Python 3 fork) 
Home-page: https://github.com/FriedrichFroebel/didjvu/
Author: Jakub Wilk
Maintainer: FriedrichFröbel
License: GPL-2.0-only
Classifier: Development Status :: 4 - Beta
Classifier: Environment :: Console
Classifier: Intended Audience :: End Users/Desktop
Classifier: License :: OSI Approved :: GNU General Public License v2 (GPLv2)
Classifier: Operating System :: OS Independent
Classifier: Programming Language :: Python
Classifier: Programming Language :: Python :: 3
Classifier: Programming Language :: Python :: 3 :: Only
Classifier: Topic :: Text Processing
Classifier: Topic :: Multimedia :: Graphics
Requires-Python: >=3.10, <4
License-File: COPYING
Requires-Dist: gamera>=4.0.0
Requires-Dist: Pillow
Provides-Extra: dev
Requires-Dist: coverage; extra == "dev"
Requires-Dist: flake8; extra == "dev"
Requires-Dist: pep8-naming; extra == "dev"
Provides-Extra: docs
Requires-Dist: docutils; extra == "docs"
Requires-Dist: pygments; extra == "docs"
Dynamic: author
Dynamic: classifier
Dynamic: description
Dynamic: description-content-type
Dynamic: home-page
Dynamic: license
Dynamic: license-file
Dynamic: maintainer
Dynamic: provides-extra
Dynamic: requires-dist
Dynamic: requires-python
Dynamic: summary
